{
  "version": "2.7.9",
  "minVersion": "2.7.7",
  "name": "StationCore v2.7.9 Panel inteligente para decisiones",
  "title": "StationCore v2.7.9",
  "downloadUrl": "https://raw.githubusercontent.com/garicabrera95/stationcore-updates/main/releases/StationCore_business_intelligence_v2_7_9.zip",
  "url": "https://raw.githubusercontent.com/garicabrera95/stationcore-updates/main/releases/StationCore_business_intelligence_v2_7_9.zip",
  "sha256": "e922723003decfbca804d858e3ac5362a6087dabdcf5cf2be5b85ec25d7ac1da",
  "size": 127167,
  "sizeBytes": 127167,
  "mandatory": false,
  "containsMigrations": false,
  "migrations": [],
  "publishedAt": "2026-07-16T22:02:56Z",
  "notes": [
    "Actualización compatible desde StationCore v2.7.7.",
    "Compara ventas con el mismo día de la semana anterior hasta la misma hora.",
    "Agrega proyección de cierre, ritmo del día y hora habitual de cierre.",
    "Agrega mapa semanal de movimiento por día y hora con ventas y ocupación.",
    "Agrega rendimiento por estación con ingresos cobrados, sesiones y utilización.",
    "Los nuevos paneles permanecen plegados por defecto.",
    "Corrige el cálculo interno de horas pico detectado durante la prueba de v2.7.8.",
    "NO contiene migraciones ni cambios de base de datos."
  ]
}
